qcio/__init__.py
qcio/helper_types.py
qcio/py.typed
qcio/qcel.py
qcio/utils.py
qcio/view.py
qcio/models/__init__.py
qcio/models/base_models.py
qcio/models/inputs.py
qcio/models/results.py
qcio/models/structure.py
qcio/models/utils.py
qcio-0.16.0.dist-info/METADATA
qcio-0.16.0.dist-info/WHEEL
qcio-0.16.0.dist-info/licenses/LICENSE
qcio-0.16.0.dist-info/RECORD
