Metadata-Version: 2.4
Name: qcio
Version: 0.16.0
Summary: Beautiful and user friendly data structures for quantum chemistry.
Project-URL: Homepage, https://github.com/coltonbh/qcio
Project-URL: Documentation, https://qcio.coltonhicks.com
Project-URL: Source, https://github.com/coltonbh/qcio
Project-URL: Changelog, https://github.com/coltonbh/qcio/blob/master/CHANGELOG.md
Project-URL: Bug Tracker, https://github.com/coltonbh/qcio/issues
Project-URL: repository, https://github.com/coltonbh/qcio
Author-email: Colton Hicks <github@coltonhicks.com>
License: The MIT License (MIT)
License-File: LICENSE
Keywords: cheminformatics,data-structures,quantum-chemistry
Classifier: Development Status :: 4 - Beta
Classifier: Intended Audience :: Developers
Classifier: Intended Audience :: Science/Research
Classifier: License :: OSI Approved :: MIT License
Classifier: Natural Language :: English
Classifier: Programming Language :: Python :: 3.10
Classifier: Programming Language :: Python :: 3.11
Classifier: Programming Language :: Python :: 3.12
Classifier: Programming Language :: Python :: 3.13
Classifier: Programming Language :: Python :: 3.14
Classifier: Topic :: Scientific/Engineering
Classifier: Topic :: Software Development :: Libraries
Requires-Python: >=3.10
Requires-Dist: eval-type-backport>=0.2.0
Requires-Dist: numpy>=1.20
Requires-Dist: pydantic!=2.0.1,!=2.1.0,>=2.0.0
Requires-Dist: pyyaml>=6.0
Requires-Dist: qcconst>=0.2.1
Requires-Dist: toml>=0.10.2
Requires-Dist: typing-extensions>=4.7.1
Provides-Extra: all
Requires-Dist: ipython>=8.0.0; extra == 'all'
Requires-Dist: matplotlib>=3.0.0; extra == 'all'
Requires-Dist: py3dmol>=2.2.1; extra == 'all'
Requires-Dist: qcinf>=0.1.1; extra == 'all'
Requires-Dist: rdkit>=2022.3.3; extra == 'all'
Provides-Extra: view
Requires-Dist: ipython>=8.0.0; extra == 'view'
Requires-Dist: matplotlib>=3.0.0; extra == 'view'
Requires-Dist: py3dmol>=2.2.1; extra == 'view'
Requires-Dist: qcinf>=0.1.1; extra == 'view'
Requires-Dist: rdkit>=2022.3.3; extra == 'view'
